{
  "kind": "collectionType",
  "collectionName": "artikels",
  "info": {
    "singularName": "artikel",
    "pluralName": "artikels",
    "displayName": "artikel",
    "description": ""
  },
  "options": {
    "draftAndPublish": true
  },
  "pluginOptions": {},
  "attributes": {
    "tittle": {
      "type": "text"
    },
    "location": {
      "type": "string"
    },
    "tanggal": {
      "type": "date"
    },
    "body": {
      "type": "text"
    },
    "images": {
      "type": "media",
      "multiple": false,
      "required": false,
      "allowedTypes": [
        "images",
        "files",
        "videos",
        "audios"
      ]
    },
    "tags": {
      "type": "string"
    }
  }
}
